<?xml version="1.0" encoding="utf-8"?>
<Catalog>
    <CSound id="THorner04Tychus00456" parent="Campaign" Portrait="TychusPortrait" Subtitle="THorner04" Speaker="CharTychus" Actor="" Line="00456">
        <AssetArray index="0">
            <File value="LocalizedData\Sounds\VO\OdinToo.ogg"/>
            <FacialAnim value="THanson03BTychus00030"/>
            <PortraitModel value="TychusPortrait"/>
            <Speaker value="ConversationState/Characters/CharTychus"/>
            <Subtitle value="Conversation/THorner04/Line00456"/>
        </AssetArray>
    </CSound>
</Catalog>
